hero_mvc_lib/__init__.py
hero_mvc_lib/controller.py
hero_mvc_lib/database.py
hero_mvc_lib/models.py
hero_mvc_lib/repository.py
hero_mvc_lib/service.py
hero_mvc_lib-0.1.0.dist-info/METADATA
hero_mvc_lib-0.1.0.dist-info/WHEEL
hero_mvc_lib-0.1.0.dist-info/top_level.txt
hero_mvc_lib-0.1.0.dist-info/RECORD
