Metadata-Version: 2.4
Name: hero-mvc-lib
Version: 0.1.0
Summary: A simple MVC library for Hero management with in-memory database support
Author-email: Hero MVC Team <hero-mvc@example.com>
License-Expression: MIT
Project-URL: Homepage, https://github.com/hero-mvc/hero-mvc-lib
Project-URL: Repository, https://github.com/hero-mvc/hero-mvc-lib
Project-URL: Documentation, https://github.com/hero-mvc/hero-mvc-lib#readme
Project-URL: Bug Tracker, https://github.com/hero-mvc/hero-mvc-lib/issues
Classifier: Development Status :: 3 - Alpha
Classifier: Intended Audience :: Developers
Classifier: Operating System :: OS Independent
Classifier: Programming Language :: Python :: 3
Classifier: Programming Language :: Python :: 3.8
Classifier: Programming Language :: Python :: 3.9
Classifier: Programming Language :: Python :: 3.10
Classifier: Programming Language :: Python :: 3.11
Requires-Python: >=3.8
Requires-Dist: sqlmodel>=0.0.24
Requires-Dist: fastapi>=0.100.0
Requires-Dist: pydantic>=2.0.0
